__init__/__init__.py
banana_king-1.0.0.dist-info/METADATA
banana_king-1.0.0.dist-info/WHEEL
banana_king-1.0.0.dist-info/entry_points.txt
banana_king-1.0.0.dist-info/top_level.txt
banana_king-1.0.0.dist-info/RECORD
